{"@class":"PhysicsBody","id":{"uuid":"9F1EF21A-6525-4D23-8B24-13AF201EB86B"},"physBodyType":"kinematic","physSurfaceType":"defaultSurfaceType","mass":10.0,"friction":10.0,"bounciness":0.5,"lockPositionX":false,"lockPositionY":false,"lockPositionZ":false,"lockRotationX":false,"lockRotationY":false,"lockRotationZ":false,"gravity":{"values":[0.0,0.0,0.0]},"useCustomGravity":false,"useCCD":false,"ccdSweptSphereRadius":0.0,"ccdMotionThreshold":0.0,"useLocalInitialVelocities":false,"initLinearVelocity":{"values":[0.0,0.0,0.0]},"initAngularVelocity":{"values":[0.0,0.0,0.0]}}